csv_convert/CONSTS.py
csv_convert/CSVFileHandler.py
csv_convert/__init__.py
csv_convert/cli.py
logging_utils/__init__.py
logging_utils/logger.py
tests/TestCSVFileHandler.py
tests/__init__.py
csv_converter_renyt-1.9.3.dist-info/LICENSE
csv_converter_renyt-1.9.3.dist-info/METADATA
csv_converter_renyt-1.9.3.dist-info/WHEEL
csv_converter_renyt-1.9.3.dist-info/entry_points.txt
csv_converter_renyt-1.9.3.dist-info/top_level.txt
csv_converter_renyt-1.9.3.dist-info/RECORD
