Metadata-Version: 2.1
Name: csv_converter_renyt
Version: 1.9.3
Summary: A tool is used to convert a .csv file separatec with delimiter to a .csv file separated with Tab: "\t"
Author: REB YuanTong
Author-email: REN YuanTong <renyt1621@mails.jlu.edu.cn>
License: MIT
License-File: LICENSE
Requires-Dist: pandas>=1.3.0
Requires-Dist: chardet>=4.0.0
